LICENSE
MANIFEST.in
README
setup.py
chiki_deploy/__init__.py
chiki_deploy/front.py
chiki_deploy/nginx.py
chiki_deploy/server.py
chiki_deploy/utils.py
chiki_deploy/web.py
chiki_deploy.egg-info/PKG-INFO
chiki_deploy.egg-info/SOURCES.txt
chiki_deploy.egg-info/dependency_links.txt
chiki_deploy.egg-info/not-zip-safe
chiki_deploy.egg-info/requires.txt
chiki_deploy.egg-info/top_level.txt