Metadata-Version: 1.0
Name: chiki-deploy
Version: 0.0.1
Summary: chiki deploy libs.
Home-page: https://github.com/endsh/chiki-deploy
Author: Linshao
Author-email: 438985635@qq.com
License: UNKNOWN
Platform: any
